PyPiUpdater/__init__.py
PyPiUpdater/multi_updater.py
PyPiUpdater/single_updater.py
pypiupdater-0.9.4.dist-info/METADATA
pypiupdater-0.9.4.dist-info/WHEEL
pypiupdater-0.9.4.dist-info/licenses/LICENSE.md
pypiupdater-0.9.4.dist-info/RECORD
